[
    {
        "url": "https://github.com/Akna/Product/blob/master/images/bananas.jpg?raw=true",
        "id": "1",
        "title": "Bananas",
        "isFavorite": false
    },
    {
        "url": "https://github.com/Akna/Product/blob/master/images/hamburgers.jpg?raw=true",
        "id": "2",
        "title": "Hamburgers",
        "isFavorite": false
    },
    {
        "url": "https://github.com/Akna/Product/blob/master/images/blueberries.jpg?raw=true",
        "id": "3",
        "title": "Blueberries",
        "isFavorite": false
    },
    {
        "url": "https://github.com/Akna/Product/blob/master/images/watermelons.jpg?raw=true",
        "id": "4",
        "title": "Watermelons",
        "isFavorite": false
    },
    {
        "url": "https://github.com/Akna/Product/blob/master/images/apples.jpg?raw=true",
        "id": "5",
        "title": "Apples",
        "isFavorite": false
    }
]
